rocc/calculation.c
rocc/py.typed
rocc/calculation.cpython-312-x86_64-linux-musl.so
rocc/calculation.pyx
rocc/__init__.py
enhydris_cache/cli.py
enhydris_cache/py.typed
enhydris_cache/enhydris_cache.py
enhydris_cache/__init__.py
pthelma/_version.py
pthelma/__init__.py
enhydris_api_client/py.typed
enhydris_api_client/__init__.py
textbisect/py.typed
textbisect/__init__.py
hspatial/test.py
hspatial/cli.py
hspatial/py.typed
hspatial/hspatial.py
hspatial/__init__.py
haggregate/regularize.cpython-312-x86_64-linux-musl.so
haggregate/regularize.c
haggregate/cli.py
haggregate/regularize.pyx
haggregate/haggregate.py
haggregate/py.typed
haggregate/regularize.pyi
haggregate/__init__.py
htimeseries/htimeseries.py
htimeseries/py.typed
htimeseries/timezone_utils.py
htimeseries/__init__.py
evaporation/evaporation.py
evaporation/cli.py
evaporation/py.typed
evaporation/__init__.py
pthelma-2.8.1.dist-info/WHEEL
pthelma-2.8.1.dist-info/entry_points.txt
pthelma-2.8.1.dist-info/top_level.txt
pthelma-2.8.1.dist-info/METADATA
pthelma-2.8.1.dist-info/RECORD
pthelma-2.8.1.dist-info/licenses/LICENSE.rst
